{
  "symbol": "EFERT",
  "cached_at": "2026-01-20T04:08:43.530776",
  "data": {
    "recommendation_buy": 0,
    "recommendation_sell": 0,
    "recommendation_neutral": 0,
    "overall_recommendation": "NEUTRAL",
    "rsi_14": 59.8,
    "stochastic_k": 44.16,
    "cci": 36.82,
    "adx": 35.31,
    "awesome_oscillator": 12.51,
    "momentum_10": -12.38,
    "macd_level": 5.87,
    "stochastic_rsi": 10.55,
    "williams_r": -52.82,
    "bull_bear_power": 5.26,
    "ultimate_oscillator": 42.79,
    "ema_10": 241.89,
    "sma_10": 245.34,
    "ema_20": 237.73,
    "sma_20": 237.0,
    "ema_30": 233.93,
    "sma_30": 230.68,
    "ema_50": 228.82,
    "sma_50": 225.35,
    "ema_100": 221.58,
    "sma_100": 221.03,
    "vwma": 243.18,
    "hma": 239.38
  }
}